dd_woodpecker
